modalmap/__init__.py
modalmap-0.0.0.dist-info/LICENSE
modalmap-0.0.0.dist-info/METADATA
modalmap-0.0.0.dist-info/WHEEL
modalmap-0.0.0.dist-info/top_level.txt
modalmap-0.0.0.dist-info/RECORD
